zlicutils/__init__.py
zlicutils/server.py
zlicutils/tan.py
zlicutils-1.1.0.dist-info/LICENSE
zlicutils-1.1.0.dist-info/METADATA
zlicutils-1.1.0.dist-info/WHEEL
zlicutils-1.1.0.dist-info/top_level.txt
zlicutils-1.1.0.dist-info/RECORD
