Metadata-Version: 2.1
Name: zlicutils
Version: 1.1.0
Summary: A library for shared classes and functionalities in the ZLiC project.
Home-page: https://github.com/dfriedenberger/zlic-tools.git
Author: Dirk Friedenberger
Author-email: projekte@frittenburger.de
License: GPLv3
Classifier: Programming Language :: Python :: 3
Classifier: License :: OSI Approved :: GNU Lesser General Public License v3 (LGPLv3)
Classifier: Operating System :: OS Independent
License-File: LICENSE
Requires-Dist: fastapi
Requires-Dist: uvicorn
